CryptoSqlite/_CryptoSqlite.cp311-win_amd64.pyd
CryptoSqlite/__init__.py
CryptoSqlite/__main__.py
CryptoSqlite/dbapi2.py
CryptoSqlite/dump.py
CryptoSqlite/sqlcipher.dll
CryptoSqlite/test/__init__.py
CryptoSqlite/test/backup.py
CryptoSqlite/test/dbapi.py
CryptoSqlite/test/dump.py
CryptoSqlite/test/factory.py
CryptoSqlite/test/hooks.py
CryptoSqlite/test/regression.py
CryptoSqlite/test/transactions.py
CryptoSqlite/test/types.py
CryptoSqlite/test/userfunctions.py
CryptoSqlite-0.0.1.dist-info/METADATA
CryptoSqlite-0.0.1.dist-info/WHEEL
CryptoSqlite-0.0.1.dist-info/top_level.txt
CryptoSqlite-0.0.1.dist-info/RECORD
