Metadata-Version: 2.1
Name: CryptoSqlite
Version: 0.0.3
Summary: python version of sqlcipher
Home-page: https://github.com/Quenwaz/CryptoSqlite
Author: zkh
Author-email: 404937333@qq.com
License: MIT License
Keywords: sqlite3,cipher
Platform: Windows
Platform: Linux
Classifier: Development Status :: 4 - Beta
Classifier: Intended Audience :: Developers
Classifier: License :: OSI Approved :: MIT License
Classifier: Operating System :: Microsoft :: Windows
Classifier: Natural Language :: Chinese (Simplified)
Classifier: Programming Language :: Python :: 3
Classifier: Topic :: Software Development :: Libraries :: Python Modules
Requires-Python: >=3.7,<4.0
License-File: LICENSE
